counter_16_bits/tester.v
/* ++++++++++++++++++++++++++++++++++++++++++++++
Tarea 1 - Probador del contador sincrónico de 4 bits.

Descripción conductual de un contador sincrónico 
de 4 bits.

Autor: Alejandro Zuniga Perez
Carne: B59097 
   ++++++++++++++++++++++++++++++++++++++++++++++ */
`ifndef TESTER_H
`define TESTER_H
`include"counter_4_bits.v"
module tester_h(w1, w2, w3, D, D_16_bits, ENB, CLK, MODO, Q, Q_16_bits,RCO);

    output reg [3:0] D;
    output reg [15:0] D_16_bits;
    output reg [1:0] MODO;
    output reg CLK;
    output reg ENB;

    input [3:0] Q;
    input [15:0] Q_16_bits;
    input w1, w2, w3;
    input RCO;

    initial 
    $monitor("Time = %d, D = %d, ENB = %b, MODO = %b, Q = %d, RCO=%b", $time,D,ENB,MODO,Q, RCO);
    
    initial
    {CLK, ENB} = 0;
    
    always begin
       #1 CLK = ~CLK;
    end


    initial begin
        $display("\nCuenta descendente 1 en 1.");
        D = 4'b0000;
        MODO = 2'b11;
        ENB = 1;
        
        #1; #1;
        MODO = 2'b00;
            #1;#1;
            #1;#1;
            #1;#1;
            #1;#1;
            #1;#1;
            #1;#1;
            #1;#1;
            #1;#1;
            #1;#1;
            #1;#1;
            #1;#1;
            #1;#1;
            #1;#1;
            #1;#1;
            #1;#1;
            #1;#1;


            $display("\nCuenta descendente 1 en 1.");
            D=4'b1111;
            MODO = 2'b11;
            ENB = 1;
            

            #1; #1;
            MODO = 2'b01;

            #1; #1;
            #1; #1;
            #1; #1;
            #1; #1;
            #1; #1;
            #1; #1;
            #1; #1;
            #1; #1;
            #1; #1;
            #1; #1;
            #1; #1;
            #1; #1;
            #1; #1;
            #1; #1;
            #1; #1;
            #1; #1;
            #1; #1;

            $display("\nCuenta descendente 3 en 3.");
            D=4'b0000;
            MODO = 2'b11;
            ENB = 1;

            #1; #1;
            MODO = 2'b10;

            #1; #1;
            #1; #1;
            #1; #1;
            #1; #1;
            #1; #1;
            #1; #1;
            #1; #1;
            
            $display("Carga en paralelo.");
            #1;
            D = 4'bXXXX;
            MODO = 4'b11;
            ENB = 1;
            #1;
            #1; D = 4'b0101;
            #2; D = 4'b1101;
            #2; D = 4'b1001;

            #1; #1;

        $monitor("Time = %d, D = %d, ENB = %b, MODO = %b, Q = %d, w1=%b, w2=%b, w3=%b", $time,D_16_bits,ENB,MODO,Q_16_bits,w1, w2, w3);        
        D_16_bits = 16'b0000000000000000;MODO = 2'b11;
        $display("\n++++++++++++++++++CONTADOR DE 16 BITS++++++++++++++++++\n");
        $display("Cuenta ascendente.");
        ENB=1;
        #1; #1;
        MODO = 2'b00;
        #2;#2;
        #2;#2;
        #2;#2;
        #2;#2;
        #2;#2;
        #2;#2;
        #2;#2;
        #2;#2;
        #2;#2;
        #2;#2;
        #2;#2;
        #2;#2;
        #2;#2;
        #2;#2;
        #2;#2;
        #2;#2;
        #2;#2;

        D_16_bits = 16'b1111111111111111; MODO = 2'b11;
        $display("Cuenta descendente");
        ENB = 1;

        #1; #1;
        MODO = 2'b01;
        #2; #2;
        #2; #2;
        #2; #2;
        #2; #2;
        #2; #2;
        #2; #2;
        #2; #2;
        #2; #2;
        #2; #2;
        #1; #1;
        #1; #1;
        #1; #1;
        #1; #1;
        #1; #1;
        #1; #1;

        D_16_bits = 16'b1111111111111111; MODO = 2'b11;
        $display("Cuenta descendente de 3 en 3");
        ENB = 1;

        #1; #1;
        MODO = 2'b10;
        #2; #2;
        #2; #2;
        #2; #2;
        #2; #2;
        #2; #2;
        #2; #2;
        #2; #2;
        #2; #2;
        #2; #2;
        #1; #1;
        #1; #1;
        #1; #1;
        #1; #1;
        #1; #1;
        #1; #1;

        $finish;
    end




endmodule

`endif

counter_16_bits/counter_4_bits.v
/* ++++++++++++++++++++++++++++++++++++++++++++++
Tarea 1 - Módulo del contador sincrónico de 4 bits.

Descripción conductual de un contador sincrónico 
de 4 bits.

Autor: Alejandro Zuniga Perez
Carne: B59097 
   ++++++++++++++++++++++++++++++++++++++++++++++ */
`ifndef COUNTER_4_BITS
`define COUNTER_4_BITS
module counter_4_bits (
    Q,
    RCO,
    D,
    ENB,
    CLK,
    MODO
);
/* Se definen las entradas y salidas del módulo,
las cuales estarán definidas gráficamente en el informe final.
Sin embargo, se definen D, los relojes, el modo, la señal ENB, y
las salidas Q y RCO.*/
    input [3:0] D;
    input [1:0] MODO;
    input ENB;
    input CLK;
    output [3:0] Q;
    reg [3:0] Q_temp;
    reg [3:0] D_temp;
    output reg RCO;
/* Se marca una condición de que cada vez que el reloj cambie de estado
en el flanco positivo o bien, que la señal enable se ejecute o marque un
valor de true, lo que indicará que se estará ejecutando una acción en el 
contador.*/
    always@(posedge CLK or ENB)
/* La logica del contador consiste en definir dos estados, representados
por los valores que puede tomar la señal ENB, los cuales son 0 y 1. De 
esta manera, se tiene que si ENB = 0 entonces no acción (los valores de Q
se mantienen en 0 pues no existe ningun estimulo para la salida). De otra
forma, si ENB = 1, se determinará a través de las posibles combinaciones de
MODO los diferentes modos de conteo del sistema. */
        begin
            if(ENB==0) begin
                // Q_temp <= Q_temp;
                Q_temp  <= 4'b0000;
                RCO <= 0;
            end
            else if(ENB==1) begin
            if(MODO==2'b00)begin
                Q_temp <= Q_temp + 1;
                RCO<=0;
                if(Q_temp == 4'b1111) begin
                    RCO<=1;
                end
                
            end
            else if(MODO==2'b01) begin
                Q_temp <= Q_temp - 1;
                RCO<=0;
                if(Q_temp <= 4'b0000)begin
                    RCO <= 1;
                end
            end
            else if(MODO == 2'b10) begin
                RCO <= 0;
                Q_temp <= Q_temp - 3;
                if(Q_temp <= 4'b0000 || Q_temp <= 4'b0001 || Q_temp <= 4'b0010)begin
                    RCO <= 1;
                end
            end
            else if (MODO == 2'b11) begin
                Q_temp <= D;
                RCO <= 0;
            end
            end
        end
// Se asigna la señal Q_temp a la señal Q para efectos de que la simulación
// no tenga problemas al momento de graficar una señal que no sea un reg.

    assign Q = Q_temp;

    
endmodule

/* El contador de 16 bits tendrá un comportamiento 
que permitirá comprobar la eficacia del contador 
de 4 bits, pues consiste en un sistema de 4 contadores
de 4 bits asociados según sus entradas y salidas. */
module counter_16_bits(Q, w1, w2, w3, w4, D, CLK, ENB, MODO);
    input [15:0] D;
    input CLK;
    input [1:0] MODO;
    input ENB;
    output [15:0] Q;
    output w1,w2, w3,w4; //RCO por cada counter de 4 bits.
    reg [15:0] Q_n;
    reg RCO_temp;
    reg ENB_temp;
    output RCO;
    wire N1, N2, N3, N4;
    reg a1, a2, a3, a4;
    wire n1, n2, n3, n4;
    reg [1:0] modo_tmp;
    initial begin 
       a1 = 0; 
       a2 = 0; 
       a3 = 0;
       RCO_temp = 0;
    end

    /* Si bien la lógica del contador de 16 bits
    debe ser básica y meramente logística, pues el 
    contador de 4 bits ya debe por sí mismo representar
    los comportamientos a gran escala, es necesario tomar
    en cuenta la funcionalidad de los relojes del módulo
    en cuestión. Sumado a este detalle, existe la necesidad 
    de ampliar la ejecución de cada contador. Es decir, estos
    contadores no entrarán en acción sincrónicamente, sino que
    su ejecución dependerá de los llevos respectivos. Estos 
    llevos son los que marcarán la señal de reloj para que sus 
    acciones sean asincrónicas y estables, para poder cumplir
    con un conteo eficiente.  */
    always @(posedge CLK or Q) begin
        /*En este punto se tiene que si el Modo está en carga
        paralela, los enable de los contadores deben estar activados,
        esto para que carguen el valor deseado.*/
        if (MODO == 2'b11) begin
            {a1, a2, a3} = 0;
        end

        /* Por otro lado, si  alguno de los llevo de los contadores son 0, 
        es posible determinar la entrada en acción de alguno de los contadores
        por efecto de que se guarda un estado anterior, por lo tanto
        significa que al menos uno de los contadores está siendo ejecutado por el 
        cambio de valor desde un RCO en 1 a un RCO en 0.*/
        if (w1 == 0 || w2 == 0 || w3 == 0) begin
            a1 = 1;
            a2 = 1;
            a3 = 1;
        end
        /* Para no generar un comportamiento inesperado en el if anterior, es necesario
        definir otros if adicionales que básicamente harán que cada contador 
        entre en acción de forma pausada y ordenada, siguiendo el orden de conteo,
        desde esta perspectiva, si el llevo del primer contador es 1, seguirá su ejecución
        y por lo tanto volverá a contar naturalmente mientras se habilita el siguiente 
        contador. Lo mismo aplica para los contadores restantes. */
        if (w1 == 1) begin
            RCO_temp <= 1;
            a1 = 1;
            
        end
        if (w2 == 1) begin
            RCO_temp <= 1;
            a2 = 1;
            
        end
        if (w3 == 1) begin
            RCO_temp <= 1;
            a3 = 1;
        end
        
    end
    assign RCO = RCO_temp;
    
    /* En este punto se asocian los cuatro contadores de 4 bits considerando especialmente
    la funcionalidad de la señal de reloj. Para efectos de mayor comprensión, favor referir-
    se al reporte escrito, donde se proyectan esquemáticos con el fin de ilustrar al lector
    de forma más amplia. */
    counter_4_bits counter_LSB(.Q(Q[3:0]), .RCO(w1), .D(D[3:0]), .ENB(ENB), .CLK(CLK), .MODO(MODO));
    counter_4_bits counter_FSB(.Q(Q[7:4]), .RCO(w2), .D(D[7:4]), .ENB(a1), .CLK(w1), .MODO(MODO));
    counter_4_bits counter_SSB(.Q(Q[11:8]), .RCO(w3), .D(D[11:8]), .ENB(a2), .CLK(w2), .MODO(MODO));
    counter_4_bits counter_MSB(.Q(Q[15:12]), .RCO(w4), .D(D[15:12]), .ENB(a3), .CLK(w3), .MODO(MODO));
    
endmodule

`endif

counter_16_bits/testbench.v
/* ++++++++++++++++++++++++++++++++++++++++++++++
Tarea 1 - testbench del contador sincrónico de 4 bits.

Descripción conductual de un contador sincrónico 
de 4 bits.

Autor: Alejandro Zuniga Perez
Carne: B59097 
   ++++++++++++++++++++++++++++++++++++++++++++++ */
`ifndef COUNTER_BENCH
`define COUNTER_BENCH
`include"counter_4_bits.v"
`include"tester.v"
module counter_bench;
    wire RCO,ENB, CLK, w1, w2, w3;
    wire [3:0] Q;
    wire [15:0] Q_16_bits;
    wire [3:0] D;
    wire [15:0] D_16_bits;
    wire [1:0] MODO;
    // reg [3:0] D;
    // reg CLK; 
    // reg [1:0] MODO;
    // reg ENB;
    // wire[3:0] Q;
    // reg[3:0] Q_temp;
    // wire RCO;

    initial begin
        $dumpfile("testbench.vcd");
        $dumpvars(-1, counter_bench);
    end
    counter_4_bits dut(.Q(Q), .RCO(RCO), .D(D), .ENB(ENB), .CLK(CLK), .MODO(MODO));
    counter_16_bits dut_16_bits(.Q(Q_16_bits), .w1(w1), .w2(w2), .w3(w3), .D(D_16_bits), .ENB(ENB), .CLK(CLK), .MODO(MODO));
    tester_h t1(.w1(w1), .w2(w2), .w3(w3), .D(D), .D_16_bits(D_16_bits), .ENB(ENB), .CLK(CLK), .MODO(MODO), .Q(Q), .Q_16_bits(Q_16_bits), .RCO(RCO));



endmodule

`endif

counter_16_bits/testbench.vcd
$date
	Sun Sep 11 23:29:12 2022
$end
$version
	Icarus Verilog
$end
$timescale
	1s
$end
$scope module counter_bench $end
$var wire 1 ! w3 $end
$var wire 1 " w2 $end
$var wire 1 # w1 $end
$var wire 1 $ RCO $end
$var wire 16 % Q_16_bits [15:0] $end
$var wire 4 & Q [3:0] $end
$var wire 2 ' MODO [1:0] $end
$var wire 1 ( ENB $end
$var wire 16 ) D_16_bits [15:0] $end
$var wire 4 * D [3:0] $end
$var wire 1 + CLK $end
$scope module dut $end
$var wire 4 , Q [3:0] $end
$var wire 2 - MODO [1:0] $end
$var wire 1 ( ENB $end
$var wire 4 . D [3:0] $end
$var wire 1 + CLK $end
$var reg 4 / Q_temp [3:0] $end
$var reg 1 $ RCO $end
$upscope $end
$scope module dut_16_bits $end
$var wire 1 0 RCO $end
$var wire 1 1 w4 $end
$var wire 1 ! w3 $end
$var wire 1 " w2 $end
$var wire 1 # w1 $end
$var wire 16 2 Q [15:0] $end
$var wire 2 3 MODO [1:0] $end
$var wire 1 ( ENB $end
$var wire 16 4 D [15:0] $end
$var wire 1 + CLK $end
$var reg 1 5 RCO_temp $end
$var reg 1 6 a1 $end
$var reg 1 7 a2 $end
$var reg 1 8 a3 $end
$scope module counter_FSB $end
$var wire 4 9 D [3:0] $end
$var wire 1 6 ENB $end
$var wire 4 : Q [3:0] $end
$var wire 2 ; MODO [1:0] $end
$var wire 1 # CLK $end
$var reg 4 < Q_temp [3:0] $end
$var reg 1 " RCO $end
$upscope $end
$scope module counter_LSB $end
$var wire 4 = D [3:0] $end
$var wire 4 > Q [3:0] $end
$var wire 2 ? MODO [1:0] $end
$var wire 1 ( ENB $end
$var wire 1 + CLK $end
$var reg 4 @ Q_temp [3:0] $end
$var reg 1 # RCO $end
$upscope $end
$scope module counter_MSB $end
$var wire 4 A D [3:0] $end
$var wire 1 8 ENB $end
$var wire 4 B Q [3:0] $end
$var wire 2 C MODO [1:0] $end
$var wire 1 ! CLK $end
$var reg 4 D Q_temp [3:0] $end
$var reg 1 1 RCO $end
$upscope $end
$scope module counter_SSB $end
$var wire 1 " CLK $end
$var wire 4 E D [3:0] $end
$var wire 1 7 ENB $end
$var wire 4 F Q [3:0] $end
$var wire 2 G MODO [1:0] $end
$var reg 4 H Q_temp [3:0] $end
$var reg 1 ! RCO $end
$upscope $end
$upscope $end
$scope module t1 $end
$var wire 4 I Q [3:0] $end
$var wire 16 J Q_16_bits [15:0] $end
$var wire 1 $ RCO $end
$var wire 1 # w1 $end
$var wire 1 " w2 $end
$var wire 1 ! w3 $end
$var reg 1 + CLK $end
$var reg 4 K D [3:0] $end
$var reg 16 L D_16_bits [15:0] $end
$var reg 1 ( ENB $end
$var reg 2 M MODO [1:0] $end
$upscope $end
$upscope $end
$enddefinitions $end
#0
$dumpvars
b11 M
bx L
b0 K
bx J
b0 I
bx H
b11 G
bx F
bx E
bx D
b11 C
bx B
bx A
bx @
b11 ?
bx >
bx =
bx <
b11 ;
bx :
bx 9
18
17
16
05
bx 4
b11 3
bx 2
01
00
b0 /
b0 .
b11 -
b0 ,
0+
b0 *
bx )
1(
b11 '
b0 &
bx %
0$
0#
0"
0!
$end
#1
16
17
18
1+
#2
b0 '
b0 -
b0 3
b0 ;
b0 ?
b0 C
b0 G
b0 M
0+
#3
b1 &
b1 ,
b1 I
b1 /
1+
#4
0+
#5
b10 &
b10 ,
b10 I
b10 /
1+
#6
0+
#7
b11 &
b11 ,
b11 I
b11 /
1+
#8
0+
#9
b100 &
b100 ,
b100 I
b100 /
1+
#10
0+
#11
b101 &
b101 ,
b101 I
b101 /
1+
#12
0+
#13
b110 &
b110 ,
b110 I
b110 /
1+
#14
0+
#15
b111 &
b111 ,
b111 I
b111 /
1+
#16
0+
#17
b1000 &
b1000 ,
b1000 I
b1000 /
1+
#18
0+
#19
b1001 &
b1001 ,
b1001 I
b1001 /
1+
#20
0+
#21
b1010 &
b1010 ,
b1010 I
b1010 /
1+
#22
0+
#23
b1011 &
b1011 ,
b1011 I
b1011 /
1+
#24
0+
#25
b1100 &
b1100 ,
b1100 I
b1100 /
1+
#26
0+
#27
b1101 &
b1101 ,
b1101 I
b1101 /
1+
#28
0+
#29
b1110 &
b1110 ,
b1110 I
b1110 /
1+
#30
0+
#31
b1111 &
b1111 ,
b1111 I
b1111 /
1+
#32
0+
#33
1$
b0 &
b0 ,
b0 I
b0 /
1+
#34
b11 '
b11 -
b11 3
b11 ;
b11 ?
b11 C
b11 G
b11 M
b1111 *
b1111 .
b1111 K
0+
#35
0$
b1111 &
b1111 ,
b1111 I
b1111 /
16
17
18
1+
#36
b1 '
b1 -
b1 3
b1 ;
b1 ?
b1 C
b1 G
b1 M
0+
#37
b1110 &
b1110 ,
b1110 I
b1110 /
1+
#38
0+
#39
b1101 &
b1101 ,
b1101 I
b1101 /
1+
#40
0+
#41
b1100 &
b1100 ,
b1100 I
b1100 /
1+
#42
0+
#43
b1011 &
b1011 ,
b1011 I
b1011 /
1+
#44
0+
#45
b1010 &
b1010 ,
b1010 I
b1010 /
1+
#46
0+
#47
b1001 &
b1001 ,
b1001 I
b1001 /
1+
#48
0+
#49
b1000 &
b1000 ,
b1000 I
b1000 /
1+
#50
0+
#51
b111 &
b111 ,
b111 I
b111 /
1+
#52
0+
#53
b110 &
b110 ,
b110 I
b110 /
1+
#54
0+
#55
b101 &
b101 ,
b101 I
b101 /
1+
#56
0+
#57
b100 &
b100 ,
b100 I
b100 /
1+
#58
0+
#59
b11 &
b11 ,
b11 I
b11 /
1+
#60
0+
#61
b10 &
b10 ,
b10 I
b10 /
1+
#62
0+
#63
b1 &
b1 ,
b1 I
b1 /
1+
#64
0+
#65
b0 &
b0 ,
b0 I
b0 /
1+
#66
0+
#67
1$
b1111 &
b1111 ,
b1111 I
b1111 /
1+
#68
0+
#69
0$
b1110 &
b1110 ,
b1110 I
b1110 /
1+
#70
b11 '
b11 -
b11 3
b11 ;
b11 ?
b11 C
b11 G
b11 M
b0 *
b0 .
b0 K
0+
#71
b0 &
b0 ,
b0 I
b0 /
16
17
18
1+
#72
b10 '
b10 -
b10 3
b10 ;
b10 ?
b10 C
b10 G
b10 M
0+
#73
1$
b1101 &
b1101 ,
b1101 I
b1101 /
1+
#74
0+
#75
b1010 &
b1010 ,
b1010 I
b1010 /
0$
1+
#76
0+
#77
b111 &
b111 ,
b111 I
b111 /
1+
#78
0+
#79
b100 &
b100 ,
b100 I
b100 /
1+
#80
0+
#81
b1 &
b1 ,
b1 I
b1 /
1+
#82
0+
#83
1$
b1110 &
b1110 ,
b1110 I
b1110 /
1+
#84
0+
#85
b1011 &
b1011 ,
b1011 I
b1011 /
0$
1+
#86
0+
#87
bx &
bx ,
bx I
bx /
16
17
18
b11 '
b11 -
b11 3
b11 ;
b11 ?
b11 C
b11 G
b11 M
bx *
bx .
bx K
1+
#88
0+
#89
b101 &
b101 ,
b101 I
b101 /
16
17
18
b101 *
b101 .
b101 K
1+
#90
0+
#91
b1101 &
b1101 ,
b1101 I
b1101 /
16
17
18
1+
b1101 *
b1101 .
b1101 K
#92
0+
#93
b1001 &
b1001 ,
b1001 I
b1001 /
16
17
18
1+
b1001 *
b1001 .
b1001 K
#94
0+
#95
b0 :
b0 <
b0 F
b0 H
b0 B
b0 D
b0 %
b0 2
b0 J
b0 >
b0 @
16
17
18
b0 A
b0 E
b0 9
b0 =
1+
b0 )
b0 4
b0 L
#96
0+
#97
b1 %
b1 2
b1 J
b1 >
b1 @
b1010 &
b1010 ,
b1010 I
b1010 /
1+
b0 '
b0 -
b0 3
b0 ;
b0 ?
b0 C
b0 G
b0 M
#98
0+
#99
b1011 &
b1011 ,
b1011 I
b1011 /
b10 %
b10 2
b10 J
b10 >
b10 @
1+
#100
0+
#101
b11 %
b11 2
b11 J
b11 >
b11 @
b1100 &
b1100 ,
b1100 I
b1100 /
1+
#102
0+
#103
b1101 &
b1101 ,
b1101 I
b1101 /
b100 %
b100 2
b100 J
b100 >
b100 @
1+
#104
0+
#105
b101 %
b101 2
b101 J
b101 >
b101 @
b1110 &
b1110 ,
b1110 I
b1110 /
1+
#106
0+
#107
b1111 &
b1111 ,
b1111 I
b1111 /
b110 %
b110 2
b110 J
b110 >
b110 @
1+
#108
0+
#109
b111 %
b111 2
b111 J
b111 >
b111 @
1$
b0 &
b0 ,
b0 I
b0 /
1+
#110
0+
#111
0$
b1 &
b1 ,
b1 I
b1 /
b1000 %
b1000 2
b1000 J
b1000 >
b1000 @
1+
#112
0+
#113
b1001 %
b1001 2
b1001 J
b1001 >
b1001 @
b10 &
b10 ,
b10 I
b10 /
1+
#114
0+
#115
b11 &
b11 ,
b11 I
b11 /
b1010 %
b1010 2
b1010 J
b1010 >
b1010 @
1+
#116
0+
#117
b1011 %
b1011 2
b1011 J
b1011 >
b1011 @
b100 &
b100 ,
b100 I
b100 /
1+
#118
0+
#119
b101 &
b101 ,
b101 I
b101 /
b1100 %
b1100 2
b1100 J
b1100 >
b1100 @
1+
#120
0+
#121
b1101 %
b1101 2
b1101 J
b1101 >
b1101 @
b110 &
b110 ,
b110 I
b110 /
1+
#122
0+
#123
b111 &
b111 ,
b111 I
b111 /
b1110 %
b1110 2
b1110 J
b1110 >
b1110 @
1+
#124
0+
#125
b1111 %
b1111 2
b1111 J
b1111 >
b1111 @
b1000 &
b1000 ,
b1000 I
b1000 /
1+
#126
0+
#127
b1 :
b1 <
10
15
b1001 &
b1001 ,
b1001 I
b1001 /
1#
b10000 %
b10000 2
b10000 J
b0 >
b0 @
1+
#128
0+
#129
0#
b10001 %
b10001 2
b10001 J
b1 >
b1 @
b1010 &
b1010 ,
b1010 I
b1010 /
1+
#130
0+
#131
b1011 &
b1011 ,
b1011 I
b1011 /
b10010 %
b10010 2
b10010 J
b10 >
b10 @
1+
#132
0+
#133
b10011 %
b10011 2
b10011 J
b11 >
b11 @
b1100 &
b1100 ,
b1100 I
b1100 /
1+
#134
0+
#135
b1101 &
b1101 ,
b1101 I
b1101 /
b10100 %
b10100 2
b10100 J
b100 >
b100 @
1+
#136
0+
#137
b10101 %
b10101 2
b10101 J
b101 >
b101 @
b1110 &
b1110 ,
b1110 I
b1110 /
1+
#138
0+
#139
b1111 &
b1111 ,
b1111 I
b1111 /
b10110 %
b10110 2
b10110 J
b110 >
b110 @
1+
#140
0+
#141
b10111 %
b10111 2
b10111 J
b111 >
b111 @
1$
b0 &
b0 ,
b0 I
b0 /
1+
#142
0+
#143
0$
b1 &
b1 ,
b1 I
b1 /
b11000 %
b11000 2
b11000 J
b1000 >
b1000 @
1+
#144
0+
#145
b11001 %
b11001 2
b11001 J
b1001 >
b1001 @
b10 &
b10 ,
b10 I
b10 /
1+
#146
0+
#147
b11 &
b11 ,
b11 I
b11 /
b11010 %
b11010 2
b11010 J
b1010 >
b1010 @
1+
#148
0+
#149
b11011 %
b11011 2
b11011 J
b1011 >
b1011 @
b100 &
b100 ,
b100 I
b100 /
1+
#150
0+
#151
b101 &
b101 ,
b101 I
b101 /
b11100 %
b11100 2
b11100 J
b1100 >
b1100 @
1+
#152
0+
#153
b11101 %
b11101 2
b11101 J
b1101 >
b1101 @
b110 &
b110 ,
b110 I
b110 /
1+
#154
0+
#155
b111 &
b111 ,
b111 I
b111 /
b11110 %
b11110 2
b11110 J
b1110 >
b1110 @
1+
#156
0+
#157
b11111 %
b11111 2
b11111 J
b1111 >
b1111 @
b1000 &
b1000 ,
b1000 I
b1000 /
1+
#158
0+
#159
b10 :
b10 <
b1001 &
b1001 ,
b1001 I
b1001 /
1#
b100000 %
b100000 2
b100000 J
b0 >
b0 @
1+
#160
0+
#161
0#
b100001 %
b100001 2
b100001 J
b1 >
b1 @
b1010 &
b1010 ,
b1010 I
b1010 /
1+
#162
0+
#163
b1011 &
b1011 ,
b1011 I
b1011 /
b100010 %
b100010 2
b100010 J
b10 >
b10 @
1+
#164
0+
#165
b1111 :
b1111 <
b1111 F
b1111 H
b1111 B
b1111 D
b1111111111111111 %
b1111111111111111 2
b1111111111111111 J
b1111 >
b1111 @
b1001 &
b1001 ,
b1001 I
b1001 /
16
17
18
b1111 A
b1111 E
b1111 9
b1111 =
1+
b11 '
b11 -
b11 3
b11 ;
b11 ?
b11 C
b11 G
b11 M
b1111111111111111 )
b1111111111111111 4
b1111111111111111 L
#166
0+
#167
b1000 &
b1000 ,
b1000 I
b1000 /
b1111111111111110 %
b1111111111111110 2
b1111111111111110 J
b1110 >
b1110 @
1+
b1 '
b1 -
b1 3
b1 ;
b1 ?
b1 C
b1 G
b1 M
#168
0+
#169
b1111111111111101 %
b1111111111111101 2
b1111111111111101 J
b1101 >
b1101 @
b111 &
b111 ,
b111 I
b111 /
1+
#170
0+
#171
b110 &
b110 ,
b110 I
b110 /
b1111111111111100 %
b1111111111111100 2
b1111111111111100 J
b1100 >
b1100 @
1+
#172
0+
#173
b1111111111111011 %
b1111111111111011 2
b1111111111111011 J
b1011 >
b1011 @
b101 &
b101 ,
b101 I
b101 /
1+
#174
0+
#175
b100 &
b100 ,
b100 I
b100 /
b1111111111111010 %
b1111111111111010 2
b1111111111111010 J
b1010 >
b1010 @
1+
#176
0+
#177
b1111111111111001 %
b1111111111111001 2
b1111111111111001 J
b1001 >
b1001 @
b11 &
b11 ,
b11 I
b11 /
1+
#178
0+
#179
b10 &
b10 ,
b10 I
b10 /
b1111111111111000 %
b1111111111111000 2
b1111111111111000 J
b1000 >
b1000 @
1+
#180
0+
#181
b1111111111110111 %
b1111111111110111 2
b1111111111110111 J
b111 >
b111 @
b1 &
b1 ,
b1 I
b1 /
1+
#182
0+
#183
b0 &
b0 ,
b0 I
b0 /
b1111111111110110 %
b1111111111110110 2
b1111111111110110 J
b110 >
b110 @
1+
#184
0+
#185
b1111111111110101 %
b1111111111110101 2
b1111111111110101 J
b101 >
b101 @
1$
b1111 &
b1111 ,
b1111 I
b1111 /
1+
#186
0+
#187
0$
b1110 &
b1110 ,
b1110 I
b1110 /
b1111111111110100 %
b1111111111110100 2
b1111111111110100 J
b100 >
b100 @
1+
#188
0+
#189
b1111111111110011 %
b1111111111110011 2
b1111111111110011 J
b11 >
b11 @
b1101 &
b1101 ,
b1101 I
b1101 /
1+
#190
0+
#191
b1100 &
b1100 ,
b1100 I
b1100 /
b1111111111110010 %
b1111111111110010 2
b1111111111110010 J
b10 >
b10 @
1+
#192
0+
#193
b1111111111110001 %
b1111111111110001 2
b1111111111110001 J
b1 >
b1 @
b1011 &
b1011 ,
b1011 I
b1011 /
1+
#194
0+
#195
b1010 &
b1010 ,
b1010 I
b1010 /
b1111111111110000 %
b1111111111110000 2
b1111111111110000 J
b0 >
b0 @
1+
#196
0+
#197
b1110 :
b1110 <
1#
b1111111111101111 %
b1111111111101111 2
b1111111111101111 J
b1111 >
b1111 @
b1001 &
b1001 ,
b1001 I
b1001 /
1+
#198
0+
#199
b1000 &
b1000 ,
b1000 I
b1000 /
0#
b1111111111101110 %
b1111111111101110 2
b1111111111101110 J
b1110 >
b1110 @
1+
#200
0+
#201
b1111111111101101 %
b1111111111101101 2
b1111111111101101 J
b1101 >
b1101 @
b111 &
b111 ,
b111 I
b111 /
1+
#202
0+
#203
b110 &
b110 ,
b110 I
b110 /
b1111111111101100 %
b1111111111101100 2
b1111111111101100 J
b1100 >
b1100 @
1+
#204
0+
#205
b1111111111101011 %
b1111111111101011 2
b1111111111101011 J
b1011 >
b1011 @
b101 &
b101 ,
b101 I
b101 /
1+
#206
0+
#207
b100 &
b100 ,
b100 I
b100 /
b1111111111101010 %
b1111111111101010 2
b1111111111101010 J
b1010 >
b1010 @
1+
#208
0+
#209
b1111111111101001 %
b1111111111101001 2
b1111111111101001 J
b1001 >
b1001 @
b11 &
b11 ,
b11 I
b11 /
1+
#210
0+
#211
b10 &
b10 ,
b10 I
b10 /
b1111111111101000 %
b1111111111101000 2
b1111111111101000 J
b1000 >
b1000 @
1+
#212
0+
#213
b1111111111100111 %
b1111111111100111 2
b1111111111100111 J
b111 >
b111 @
b1 &
b1 ,
b1 I
b1 /
1+
#214
0+
#215
b1111 :
b1111 <
b1001 &
b1001 ,
b1001 I
b1001 /
b1111111111111111 %
b1111111111111111 2
b1111111111111111 J
b1111 >
b1111 @
16
17
18
1+
b11 '
b11 -
b11 3
b11 ;
b11 ?
b11 C
b11 G
b11 M
#216
0+
#217
b1111111111111100 %
b1111111111111100 2
b1111111111111100 J
b1100 >
b1100 @
b110 &
b110 ,
b110 I
b110 /
1+
b10 '
b10 -
b10 3
b10 ;
b10 ?
b10 C
b10 G
b10 M
#218
0+
#219
b11 &
b11 ,
b11 I
b11 /
b1111111111111001 %
b1111111111111001 2
b1111111111111001 J
b1001 >
b1001 @
1+
#220
0+
#221
b1111111111110110 %
b1111111111110110 2
b1111111111110110 J
b110 >
b110 @
b0 &
b0 ,
b0 I
b0 /
1+
#222
0+
#223
1$
b1101 &
b1101 ,
b1101 I
b1101 /
b1111111111110011 %
b1111111111110011 2
b1111111111110011 J
b11 >
b11 @
1+
#224
0+
#225
b1111111111110000 %
b1111111111110000 2
b1111111111110000 J
b0 >
b0 @
b1010 &
b1010 ,
b1010 I
b1010 /
0$
1+
#226
0+
#227
b1100 :
b1100 <
b111 &
b111 ,
b111 I
b111 /
1#
b1111111111001101 %
b1111111111001101 2
b1111111111001101 J
b1101 >
b1101 @
1+
#228
0+
#229
b1111111111001010 %
b1111111111001010 2
b1111111111001010 J
b1010 >
b1010 @
0#
b100 &
b100 ,
b100 I
b100 /
1+
#230
0+
#231
b1 &
b1 ,
b1 I
b1 /
b1111111111000111 %
b1111111111000111 2
b1111111111000111 J
b111 >
b111 @
1+
#232
0+
#233
b1111111111000100 %
b1111111111000100 2
b1111111111000100 J
b100 >
b100 @
1$
b1110 &
b1110 ,
b1110 I
b1110 /
1+
#234
0+
#235
b1011 &
b1011 ,
b1011 I
b1011 /
0$
b1111111111000001 %
b1111111111000001 2
b1111111111000001 J
b1 >
b1 @
1+
#236
0+
#237
b1001 :
b1001 <
1#
b1111111110011110 %
b1111111110011110 2
b1111111110011110 J
b1110 >
b1110 @
b1000 &
b1000 ,
b1000 I
b1000 /
1+
#238
0+
#239
b101 &
b101 ,
b101 I
b101 /
b1111111110011011 %
b1111111110011011 2
b1111111110011011 J
b1011 >
b1011 @
0#
1+
#240
0+
#241
b1111111110011000 %
b1111111110011000 2
b1111111110011000 J
b1000 >
b1000 @
b10 &
b10 ,
b10 I
b10 /
1+
#242
0+
#243
1$
b1111 &
b1111 ,
b1111 I
b1111 /
b1111111110010101 %
b1111111110010101 2
b1111111110010101 J
b101 >
b101 @
1+
#244
0+
#245
b1111111110010010 %
b1111111110010010 2
b1111111110010010 J
b10 >
b10 @
b1100 &
b1100 ,
b1100 I
b1100 /
0$
1+
#246
0+
#247
b110 :
b110 <
b1001 &
b1001 ,
b1001 I
b1001 /
1#
b1111111101101111 %
b1111111101101111 2
b1111111101101111 J
b1111 >
b1111 @
1+
#248
0+
