decoders/decoder_2_4.v
`ifndef encoder_2_4
`define encoder_2_4
module encoder_2_4(y, en, I);

  input [1:0]I;
  input en;
  output reg [3:0]y;

  always@(*)
    begin
      case({en, I})
		3'b100: y = 4'b0001;
		3'b101: y = 4'b0010;
		3'b110: y = 4'b0100;
		3'b111: y = 4'b1000;
		3'b000,
		3'b001,
		3'b010,
		3'b011: y = 4'b0000;
	default: $display("Invalid combinations.");
      endcase
    end
endmodule

`endif

decoders/decoder_tb.v
`ifndef decoder_tb
`define decoder_tb

`include "decoder_2_4.v"

module decoder_tb;
    reg [1:0]I;
    reg en;
    wire [3:0]y;

    encoder_2_4 encoder_bits(.y(y), .en(en), .I(I));
    initial $monitor("time: %d, I = %b, EN = %b, y = %b ", $time, I, en, y);

    initial 
        begin
            {en, I} = 3'b000;
            $dumpfile("encoder_bench.vcd");
            $dumpvars(0, decoder_tb);
            begin
                repeat(2);
                    #10; {en, I} = 3'b100;
                    #10; {en, I} = 3'b101;
                    #10; {en, I} = 3'b110;
                    #10; {en, I} = 3'b111;
                    #10; {en, I} = 3'b000;
                    #10; {en, I} = 3'b001;
                    #10; {en, I} = 3'b010;
                    #10; {en, I} = 3'b011;
            end
        end
endmodule

`endif

decoders/encoder_bench.vcd
$date
	Sat Aug 27 21:41:06 2022
$end
$version
	Icarus Verilog
$end
$timescale
	1s
$end
$scope module decoder_tb $end
$var wire 4 ! y [3:0] $end
$var reg 2 " I [1:0] $end
$var reg 1 # en $end
$scope module encoder_bits $end
$var wire 2 $ I [1:0] $end
$var wire 1 # en $end
$var reg 4 % y [3:0] $end
$upscope $end
$upscope $end
$enddefinitions $end
#0
$dumpvars
b0 %
b0 $
0#
b0 "
b0 !
$end
#10
b1 !
b1 %
1#
#20
b10 !
b10 %
b1 "
b1 $
#30
b100 !
b100 %
b10 "
b10 $
#40
b1000 !
b1000 %
b11 "
b11 $
#50
b0 !
b0 %
0#
b0 "
b0 $
#60
b1 "
b1 $
#70
b10 "
b10 $
#80
b11 "
b11 $
