alu_4_bits/mux_4_bits.v
`ifndef MUX_4_BITS
`define MUX_4_BITS

module mux_4bits (
    y, fa, a, b, c, M
);
    input fa, a, b, c ;
    input[1:0] M;
    output reg y;
    
    always @(*)
        case(M)
            2'b00: y = fa;
            2'b01: y = a;
            2'b10: y = b;
            2'b11: y = c;
        default $display("error, y=%b,%b", M[0], M[1]);
        endcase

endmodule

`endif

alu_4_bits/xor.v
`ifndef XOR_BH
`define XOR_BH

module xor_bh(y, a, b);
    input a,b;
    output reg y;

    always@(*)
        y = a ^ b;

endmodule
`endif

alu_4_bits/or.v
`ifndef OR_BH
`define OR_BH

module or_bh(y, a, b);
    input a,b;
    output reg y;

    always@(*)
        y = a | b;

endmodule
`endif

alu_4_bits/and.v
`ifndef AND_BH
`define AND_BH

module and_bh(y, a, b);
    input a,b;
    output reg y;

    always@(*)
        y = a & b;

endmodule
`endif

alu_4_bits/full_adder.v
`ifndef FULLADDER_BH
`define FULLADDER_BH

module fulladder_bh(s,c, a, b, cin);
    input a,b;
    input cin;
    output reg s, c;

    always@(*) begin
        s = a ^ b ^ cin;
        c = a & b | b & cin | cin & a;
    end
endmodule
`endif

alu_4_bits/alu_1_bit.v
`ifndef ALU_1_BIT
`define ALU_1_BIT
`include "and.v"
`include "or.v"
`include "xor.v"
`include "mux_4_bits.v"
`include "full_adder.v"

module alu_1_bit(f, cout, a, b, cin, M);
    input a, b, cin;
    input [1:0]M;
    wire n1, n2, n3;
    wire fa;
    output cout;
    output f;


    fulladder_bh f_adder(fa, cout, a ,b ,cin);
    and_bh n_and(n1, a, b);
    or_bh n_or(n2, a, b);
    xor_bh n_xor(n3, a , b);
    mux_4bits n_mux(f, fa, n1, n2, n3, M);

    // y, fa, a, b, c


endmodule
`endif

alu_4_bits/alu_4_bits.v
`ifndef ALU_4_BITS
`define ALU_4_BITS

`include"alu_1_bit.v"

module alu_4_bits(f, cout, a, b, cin, M);
    input [3:0] a, b;
    input cin;
    input[1:0] M;
    output [3:0] f;
    output cout;
    output c1, c2, c3;

    alu_1_bit first_alu(.f(f[0]), .cout(cout),.a(a[0]), .b(b[0]), .cin(cin), .M(M));
    alu_1_bit second_alu(.f(f[1]), .cout(c1),.a(a[1]), .b(b[1]), .cin(cout), .M(M));
    alu_1_bit third_alu(.f(f[2]), .cout(c2),.a(a[2]), .b(b[2]), .cin(c1), .M(M));
    alu_1_bit fourth_alu(.f(f[3]), .cout(c3),.a(a[3]), .b(b[3]), .cin(c2), .M(M));

endmodule

`endif

alu_4_bits/alu_testbench.v
`ifndef ALU_BENCH
`define ALU_BENCH
`include "alu_4_bits.v"

module alu_bench;
    reg[3:0] a, b;
    reg cin;
    reg [1:0] M;
    wire  [3:0] f;
    wire cout;

    alu_4_bits alu_test(f, cout, a, b, cin, M);
    initial
    $monitor("time=%d, a = %b, b = %b, cin = %b, M = %b, f = %b, cout = %b", $time, a, b, cin, M, f, cout);

    initial begin
        $dumpfile("alu_bench.vcd");
        $dumpvars(0, alu_bench);
        a = 4'b0000;
        b = 4'b0000;
        M = 2'b00;
        cin = 0;
        begin
            #10; a = 4'b0000; b = 4'b0000; M = 2'b00; cin=1;
            #10; a = 4'b0001; b = 4'b0001; M = 2'b01; cin=0;
            #10; a = 4'b0010; b = 4'b0010; M = 2'b10; cin=1;
            #10; a = 4'b0011; b = 4'b0011; M = 2'b11; cin=0;
            #10; a = 4'b0100; b = 4'b0100; M = 2'b00; cin=1;
            #10; a = 4'b0101; b = 4'b0101; M = 2'b01; cin=0;
            #10; a = 4'b0110; b = 4'b0110; M = 2'b10; cin=1;
            #10; a = 4'b0111; b = 4'b0111; M = 2'b11; cin=0;
            #10; a = 4'b1000; b = 4'b1000; M = 2'b00; cin=1;
            #10; a = 4'b1001; b = 4'b1001; M = 2'b01; cin=0;
            #10; a = 4'b1010; b = 4'b1010; M = 2'b10; cin=1;
            #10; a = 4'b1011; b = 4'b1011; M = 2'b11; cin=0;
            #10; a = 4'b1100; b = 4'b1100; M = 2'b00; cin=1;
            #10; a = 4'b1101; b = 4'b1101; M = 2'b01; cin=0;
            #10; a = 4'b1110; b = 4'b1110; M = 2'b10; cin=1;
            #10; a = 4'b1111; b = 4'b1111; M = 2'b11; cin=0;
        end
    end



endmodule




`endif

alu_4_bits/alu_bench.vcd
$date
	Sun Aug 28 01:40:28 2022
$end
$version
	Icarus Verilog
$end
$timescale
	1s
$end
$scope module alu_bench $end
$var wire 4 ! f [3:0] $end
$var wire 1 " cout $end
$var reg 2 # M [1:0] $end
$var reg 4 $ a [3:0] $end
$var reg 4 % b [3:0] $end
$var reg 1 & cin $end
$scope module alu_test $end
$var wire 2 ' M [1:0] $end
$var wire 4 ( a [3:0] $end
$var wire 4 ) b [3:0] $end
$var wire 1 & cin $end
$var wire 4 * f [3:0] $end
$var wire 1 " cout $end
$var wire 1 + c3 $end
$var wire 1 , c2 $end
$var wire 1 - c1 $end
$scope module first_alu $end
$var wire 2 . M [1:0] $end
$var wire 1 / a $end
$var wire 1 0 b $end
$var wire 1 & cin $end
$var wire 1 1 n3 $end
$var wire 1 2 n2 $end
$var wire 1 3 n1 $end
$var wire 1 4 fa $end
$var wire 1 5 f $end
$var wire 1 " cout $end
$scope module f_adder $end
$var wire 1 / a $end
$var wire 1 0 b $end
$var wire 1 & cin $end
$var reg 1 " c $end
$var reg 1 4 s $end
$upscope $end
$scope module n_and $end
$var wire 1 / a $end
$var wire 1 0 b $end
$var reg 1 3 y $end
$upscope $end
$scope module n_mux $end
$var wire 2 6 M [1:0] $end
$var wire 1 3 a $end
$var wire 1 4 fa $end
$var wire 1 1 c $end
$var wire 1 2 b $end
$var reg 1 5 y $end
$upscope $end
$scope module n_or $end
$var wire 1 / a $end
$var wire 1 0 b $end
$var reg 1 2 y $end
$upscope $end
$scope module n_xor $end
$var wire 1 / a $end
$var wire 1 0 b $end
$var reg 1 1 y $end
$upscope $end
$upscope $end
$scope module fourth_alu $end
$var wire 2 7 M [1:0] $end
$var wire 1 8 a $end
$var wire 1 9 b $end
$var wire 1 : n3 $end
$var wire 1 ; n2 $end
$var wire 1 < n1 $end
$var wire 1 = fa $end
$var wire 1 > f $end
$var wire 1 + cout $end
$var wire 1 , cin $end
$scope module f_adder $end
$var wire 1 8 a $end
$var wire 1 9 b $end
$var wire 1 , cin $end
$var reg 1 + c $end
$var reg 1 = s $end
$upscope $end
$scope module n_and $end
$var wire 1 8 a $end
$var wire 1 9 b $end
$var reg 1 < y $end
$upscope $end
$scope module n_mux $end
$var wire 2 ? M [1:0] $end
$var wire 1 < a $end
$var wire 1 = fa $end
$var wire 1 : c $end
$var wire 1 ; b $end
$var reg 1 > y $end
$upscope $end
$scope module n_or $end
$var wire 1 8 a $end
$var wire 1 9 b $end
$var reg 1 ; y $end
$upscope $end
$scope module n_xor $end
$var wire 1 8 a $end
$var wire 1 9 b $end
$var reg 1 : y $end
$upscope $end
$upscope $end
$scope module second_alu $end
$var wire 2 @ M [1:0] $end
$var wire 1 A a $end
$var wire 1 B b $end
$var wire 1 " cin $end
$var wire 1 C n3 $end
$var wire 1 D n2 $end
$var wire 1 E n1 $end
$var wire 1 F fa $end
$var wire 1 G f $end
$var wire 1 - cout $end
$scope module f_adder $end
$var wire 1 A a $end
$var wire 1 B b $end
$var wire 1 " cin $end
$var reg 1 - c $end
$var reg 1 F s $end
$upscope $end
$scope module n_and $end
$var wire 1 A a $end
$var wire 1 B b $end
$var reg 1 E y $end
$upscope $end
$scope module n_mux $end
$var wire 2 H M [1:0] $end
$var wire 1 E a $end
$var wire 1 F fa $end
$var wire 1 C c $end
$var wire 1 D b $end
$var reg 1 G y $end
$upscope $end
$scope module n_or $end
$var wire 1 A a $end
$var wire 1 B b $end
$var reg 1 D y $end
$upscope $end
$scope module n_xor $end
$var wire 1 A a $end
$var wire 1 B b $end
$var reg 1 C y $end
$upscope $end
$upscope $end
$scope module third_alu $end
$var wire 2 I M [1:0] $end
$var wire 1 J a $end
$var wire 1 K b $end
$var wire 1 - cin $end
$var wire 1 L n3 $end
$var wire 1 M n2 $end
$var wire 1 N n1 $end
$var wire 1 O fa $end
$var wire 1 P f $end
$var wire 1 , cout $end
$scope module f_adder $end
$var wire 1 J a $end
$var wire 1 K b $end
$var wire 1 - cin $end
$var reg 1 , c $end
$var reg 1 O s $end
$upscope $end
$scope module n_and $end
$var wire 1 J a $end
$var wire 1 K b $end
$var reg 1 N y $end
$upscope $end
$scope module n_mux $end
$var wire 2 Q M [1:0] $end
$var wire 1 N a $end
$var wire 1 O fa $end
$var wire 1 L c $end
$var wire 1 M b $end
$var reg 1 P y $end
$upscope $end
$scope module n_or $end
$var wire 1 J a $end
$var wire 1 K b $end
$var reg 1 M y $end
$upscope $end
$scope module n_xor $end
$var wire 1 J a $end
$var wire 1 K b $end
$var reg 1 L y $end
$upscope $end
$upscope $end
$upscope $end
$upscope $end
$enddefinitions $end
#0
$dumpvars
b0 Q
0P
0O
0N
0M
0L
0K
0J
b0 I
b0 H
0G
0F
0E
0D
0C
0B
0A
b0 @
b0 ?
0>
0=
0<
0;
0:
09
08
b0 7
b0 6
05
04
03
02
01
00
0/
b0 .
0-
0,
0+
b0 *
b0 )
b0 (
b0 '
0&
b0 %
b0 $
b0 #
0"
b0 !
$end
#10
b1 !
b1 *
15
14
1&
#20
1F
13
12
1"
04
b1 !
b1 *
15
10
1/
0&
b1 #
b1 '
b1 .
b1 6
b1 7
b1 ?
b1 @
b1 H
b1 I
b1 Q
b1 %
b1 )
b1 $
b1 (
#30
1O
1G
b10 !
b10 *
05
02
03
1-
0F
1E
1D
0"
14
00
1B
0/
1A
1&
b10 #
b10 '
b10 .
b10 6
b10 7
b10 ?
b10 @
b10 H
b10 I
b10 Q
b10 %
b10 )
b10 $
b10 (
#40
1F
13
12
1"
04
b0 !
b0 *
0G
10
1/
0&
b11 #
b11 '
b11 .
b11 6
b11 7
b11 ?
b11 @
b11 H
b11 I
b11 Q
b11 %
b11 )
b11 $
b11 (
#50
1>
0O
1=
15
02
03
0-
0F
0D
0E
1,
1N
1M
0"
14
0G
b1001 !
b1001 *
0P
00
0B
1K
0/
0A
1J
1&
b0 #
b0 '
b0 .
b0 6
b0 7
b0 ?
b0 @
b0 H
b0 I
b0 Q
b100 %
b100 )
b100 $
b100 (
#60
1F
13
12
1"
04
15
0>
b101 !
b101 *
1P
10
1/
0&
b1 #
b1 '
b1 .
b1 6
b1 7
b1 ?
b1 @
b1 H
b1 I
b1 Q
b101 %
b101 )
b101 $
b101 (
#70
1O
1G
b110 !
b110 *
05
02
03
1-
0F
1E
1D
0"
14
00
1B
0/
1A
1&
b10 #
b10 '
b10 .
b10 6
b10 7
b10 ?
b10 @
b10 H
b10 I
b10 Q
b110 %
b110 )
b110 $
b110 (
#80
1F
13
12
1"
04
0G
b0 !
b0 *
0P
10
1/
0&
b11 #
b11 '
b11 .
b11 6
b11 7
b11 ?
b11 @
b11 H
b11 I
b11 Q
b111 %
b111 )
b111 $
b111 (
#90
0O
0=
15
02
03
0-
0F
0D
0E
0,
0M
0N
1+
1<
1;
0"
14
0>
0G
b1 !
b1 *
0P
00
0B
0K
19
0/
0A
0J
18
1&
b0 #
b0 '
b0 .
b0 6
b0 7
b0 ?
b0 @
b0 H
b0 I
b0 Q
b1000 %
b1000 )
b1000 $
b1000 (
#100
1F
13
12
1"
04
15
b1001 !
b1001 *
1>
10
1/
0&
b1 #
b1 '
b1 .
b1 6
b1 7
b1 ?
b1 @
b1 H
b1 I
b1 Q
b1001 %
b1001 )
b1001 $
b1001 (
#110
1O
1G
b1010 !
b1010 *
05
02
03
1-
0F
1E
1D
0"
14
00
1B
0/
1A
1&
b10 #
b10 '
b10 .
b10 6
b10 7
b10 ?
b10 @
b10 H
b10 I
b10 Q
b1010 %
b1010 )
b1010 $
b1010 (
#120
1F
13
12
1"
04
0>
b0 !
b0 *
0G
10
1/
0&
b11 #
b11 '
b11 .
b11 6
b11 7
b11 ?
b11 @
b11 H
b11 I
b11 Q
b1011 %
b1011 )
b1011 $
b1011 (
#130
1>
0O
1=
15
02
03
0-
0F
0D
0E
1,
1N
1M
0"
14
0G
b1001 !
b1001 *
0P
00
0B
1K
0/
0A
1J
1&
b0 #
b0 '
b0 .
b0 6
b0 7
b0 ?
b0 @
b0 H
b0 I
b0 Q
b1100 %
b1100 )
b1100 $
b1100 (
#140
1F
13
12
1"
04
15
b1101 !
b1101 *
1P
10
1/
0&
b1 #
b1 '
b1 .
b1 6
b1 7
b1 ?
b1 @
b1 H
b1 I
b1 Q
b1101 %
b1101 )
b1101 $
b1101 (
#150
1O
1G
b1110 !
b1110 *
05
02
03
1-
0F
1E
1D
0"
14
00
1B
0/
1A
1&
b10 #
b10 '
b10 .
b10 6
b10 7
b10 ?
b10 @
b10 H
b10 I
b10 Q
b1110 %
b1110 )
b1110 $
b1110 (
#160
1F
13
12
1"
04
0>
0G
b0 !
b0 *
0P
10
1/
0&
b11 #
b11 '
b11 .
b11 6
b11 7
b11 ?
b11 @
b11 H
b11 I
b11 Q
b1111 %
b1111 )
b1111 $
b1111 (
